flashsimplelogger/__init__.py
flashsimplelogger/logger.py
flashsimplelogger-0.1.0.dist-info/licenses/LICENSE
flashsimplelogger-0.1.0.dist-info/METADATA
flashsimplelogger-0.1.0.dist-info/WHEEL
flashsimplelogger-0.1.0.dist-info/top_level.txt
flashsimplelogger-0.1.0.dist-info/RECORD
