Metadata-Version: 2.4
Name: flashsimplelogger
Version: 0.1.0
Summary: A minimal Python logging wrapper
Home-page: https://github.com/dankorchunov89/simplelogger
Author: Dan Korchunov
Author-email: dankorchuno89@gmail.com
License: MIT
Classifier: Programming Language :: Python :: 3
Classifier: Operating System :: OS Independent
Requires-Python: >=3.6
License-File: LICENSE
Dynamic: author
Dynamic: author-email
Dynamic: classifier
Dynamic: description
Dynamic: description-content-type
Dynamic: home-page
Dynamic: license
Dynamic: license-file
Dynamic: requires-python
Dynamic: summary
